{
    "parent": "minecraft:block/beehive",
    "overrides":[
        {"predicate":{"custom_model_data":1430000},"model":"simpledrawer:block/drawer/drawer_wood_"},
        {"predicate":{"custom_model_data":1430001},"model":"simpledrawer:block/drawer/drawer_wood_tapped"},
        {"predicate":{"custom_model_data":1430002},"model":"simpledrawer:block/drawer/drawer_wood__hopper"},
        {"predicate":{"custom_model_data":1430003},"model":"simpledrawer:block/drawer/drawer_wood_tapped_hopper"},

        {"predicate":{"custom_model_data":1430004},"model":"simpledrawer:block/drawer/drawer_iron_"},
        {"predicate":{"custom_model_data":1430005},"model":"simpledrawer:block/drawer/drawer_iron_tapped"},
        {"predicate":{"custom_model_data":1430006},"model":"simpledrawer:block/drawer/drawer_iron__hopper"},
        {"predicate":{"custom_model_data":1430007},"model":"simpledrawer:block/drawer/drawer_iron_tapped_hopper"},

        {"predicate":{"custom_model_data":1430008},"model":"simpledrawer:block/drawer/drawer_gold_"},
        {"predicate":{"custom_model_data":1430009},"model":"simpledrawer:block/drawer/drawer_gold_tapped"},
        {"predicate":{"custom_model_data":1430010},"model":"simpledrawer:block/drawer/drawer_gold__hopper"},
        {"predicate":{"custom_model_data":1430011},"model":"simpledrawer:block/drawer/drawer_gold_tapped_hopper"},

        {"predicate":{"custom_model_data":1430012},"model":"simpledrawer:block/drawer/drawer_diamond_"},
        {"predicate":{"custom_model_data":1430013},"model":"simpledrawer:block/drawer/drawer_diamond_tapped"},
        {"predicate":{"custom_model_data":1430014},"model":"simpledrawer:block/drawer/drawer_diamond__hopper"},
        {"predicate":{"custom_model_data":1430015},"model":"simpledrawer:block/drawer/drawer_diamond_tapped_hopper"},

        {"predicate":{"custom_model_data":1430016},"model":"simpledrawer:block/drawer/drawer_star_"},
        {"predicate":{"custom_model_data":1430017},"model":"simpledrawer:block/drawer/drawer_star_tapped"},
        {"predicate":{"custom_model_data":1430018},"model":"simpledrawer:block/drawer/drawer_star__hopper"},
        {"predicate":{"custom_model_data":1430019},"model":"simpledrawer:block/drawer/drawer_star_tapped_hopper"},

        {"predicate":{"custom_model_data":1430020},"model":"simpledrawer:block/drawer/drawer_netherite_"},
        {"predicate":{"custom_model_data":1430021},"model":"simpledrawer:block/drawer/drawer_netherite_tapped"},
        {"predicate":{"custom_model_data":1430022},"model":"simpledrawer:block/drawer/drawer_netherite__hopper"},
        {"predicate":{"custom_model_data":1430023},"model":"simpledrawer:block/drawer/drawer_netherite_tapped_hopper"}

    ]
}
